be_datahive/__init__.py
be_datahive/be_datahive.py
be_datahive-0.1.3.dist-info/METADATA
be_datahive-0.1.3.dist-info/WHEEL
be_datahive-0.1.3.dist-info/top_level.txt
be_datahive-0.1.3.dist-info/RECORD
