Metadata-Version: 2.1
Name: be-datahive
Version: 0.1.3
Summary: A Python wrapper for the BEDATAHIVE API
Home-page: https://github.com/Lucas749/be_datahive
Author: Lucas Schneider
Author-email: lucas.schneider@cs.ox.ac.uk
License: UNKNOWN
Platform: UNKNOWN
Classifier: Development Status :: 3 - Alpha
Classifier: License :: OSI Approved :: MIT License
Classifier: Programming Language :: Python :: 3.9
Requires-Dist: requests
Requires-Dist: pandas
Requires-Dist: numpy
